pydoit_project_builder/__init__.py
pydoit_project_builder/_os_utils.py
pydoit_project_builder/_task_creator.py
pydoit_project_builder/_task_instatiation.py
test/__init__.py
test/test_os_utils.py
test/test_task_creator.py
pydoit_project_builder-0.1.0.dist-info/LICENSE
pydoit_project_builder-0.1.0.dist-info/METADATA
pydoit_project_builder-0.1.0.dist-info/WHEEL
pydoit_project_builder-0.1.0.dist-info/top_level.txt
pydoit_project_builder-0.1.0.dist-info/RECORD
