Metadata-Version: 2.1
Name: pydoit-project-builder
Version: 0.1.0
Summary: Templates to be used when creating projects.
Home-page: https://github.com/schneiderlo/pydoit-project-builder
Author: Loïc Schneider
License: Apache 2
Platform: UNKNOWN
Provides-Extra: dev
Requires-Dist: wheel; extra == 'dev'
Requires-Dist: pylint; extra == 'dev'
Requires-Dist: flake8; extra == 'dev'
Requires-Dist: flake8-docstrings; extra == 'dev'
Requires-Dist: pytest; extra == 'dev'
Requires-Dist: pytest-cov; extra == 'dev'
Requires-Dist: pytest-html; extra == 'dev'
Requires-Dist: pytest-xdist; extra == 'dev'
Requires-Dist: coverage; extra == 'dev'
